pyscnn-0.0.10.dist-info/licenses/LICENSE
scnn/__init__.py
scnn/activations.py
scnn/loss_functions.py
scnn/metrics.py
scnn/models.py
scnn/optimize.py
scnn/py.typed
scnn/regularizers.py
scnn/solvers.py
scnn/support.py
scnn/private/__init__.py
scnn/private/initializers.py
scnn/private/loss_functions.py
scnn/private/metrics.py
scnn/private/interface/__init__.py
scnn/private/interface/data.py
scnn/private/interface/metrics.py
scnn/private/interface/models.py
scnn/private/interface/solvers.py
scnn/private/interface/utils.py
scnn/private/methods/__init__.py
scnn/private/methods/callbacks.py
scnn/private/methods/external_solver.py
scnn/private/methods/method_utils.py
scnn/private/methods/processing.py
scnn/private/methods/termination_criteria.py
scnn/private/methods/core/__init__.py
scnn/private/methods/core/augmented_lagrangian.py
scnn/private/methods/core/gradient_descent.py
scnn/private/methods/core/line_search.py
scnn/private/methods/core/proximal_gradient.py
scnn/private/methods/cvxpy/__init__.py
scnn/private/methods/cvxpy/cone_decomposition.py
scnn/private/methods/cvxpy/cvxpy_solver.py
scnn/private/methods/cvxpy/training_programs.py
scnn/private/methods/line_search/__init__.py
scnn/private/methods/line_search/backtrack.py
scnn/private/methods/line_search/conditions.py
scnn/private/methods/line_search/step_size_updates.py
scnn/private/methods/optimization_procedures/__init__.py
scnn/private/methods/optimization_procedures/double_loop_procedure.py
scnn/private/methods/optimization_procedures/iterative.py
scnn/private/methods/optimization_procedures/optimization_procedure.py
scnn/private/methods/optimization_procedures/torch_loop.py
scnn/private/methods/optimizers/__init__.py
scnn/private/methods/optimizers/augmented_lagrangian.py
scnn/private/methods/optimizers/fista.py
scnn/private/methods/optimizers/gd.py
scnn/private/methods/optimizers/meta_optimizer.py
scnn/private/methods/optimizers/optimizer.py
scnn/private/methods/optimizers/pgd.py
scnn/private/methods/optimizers/proximal_optimizer.py
pyscnn-0.0.10.dist-info/METADATA
pyscnn-0.0.10.dist-info/WHEEL
pyscnn-0.0.10.dist-info/top_level.txt
pyscnn-0.0.10.dist-info/RECORD
