Metadata-Version: 2.4
Name: pyscnn
Version: 0.0.10
Summary: Scalable Convex Neural Networks: a package for fasts convex optimization of shallow neural networks.
Author-email: Aaron Mishkin <amishkin@cs.stanford.edu>
License: MIT License
Project-URL: Homepage, https://github.com/pilancilab/scnn
Project-URL: Bug Tracker, https://github.com/pilancilab/scnn/issues
Classifier: Programming Language :: Python :: 3
Classifier: License :: OSI Approved :: MIT License
Classifier: Operating System :: OS Independent
Requires-Python: >=3.7
License-File: LICENSE
Requires-Dist: numpy
Requires-Dist: torch
Requires-Dist: torchvision
Requires-Dist: cvxpy
Requires-Dist: scikit-learn
Requires-Dist: scipy
Requires-Dist: typing_extensions
Requires-Dist: tqdm
Requires-Dist: opt_einsum
Requires-Dist: linalg_backends
Dynamic: license-file
